{
    "inicio": {
        "texto": "[TEST] Carta 1 de 2. Swipe izquierda dos veces para morir.",
        "img": "/static/img/biggie.png",
        "opcion_izq": {
            "texto": "Izquierda (-60 salud)",
            "siguiente_id": "carta_muerte",
            "efectos": {
                "salud": -41,
                "dinero": 0,
                "intelecto": 0,
                "laboral": 0,
                "social": 0
            }
        },
        "opcion_der": {
            "texto": "Derecha (sin efecto)",
            "siguiente_id": "carta_muerte",
            "efectos": {
                "salud": 0,
                "dinero": 0,
                "intelecto": 0,
                "laboral": 0,
                "social": 0
            }
        }
    },
    "carta_muerte": {
        "texto": "[TEST] Carta 2 de 2. Swipe izquierda para morir ahora.",
        "img": "",
        "opcion_izq": {
            "texto": "Izquierda (-60 salud) -> MUERTE GARANTIZADA",
            "siguiente_id": "fin",
            "efectos": {
                "salud": -60,
                "dinero": 0,
                "intelecto": 0,
                "laboral": 0,
                "social": 0
            }
        },
        "opcion_der": {
            "texto": "Derecha (sin efecto)",
            "siguiente_id": "fin",
            "efectos": {
                "salud": 0,
                "dinero": 0,
                "intelecto": 0,
                "laboral": 0,
                "social": 0
            }
        }
    }
}